getools/__init__.py
getools/cross.py
getools/popdist.py
getools/utils/__init__.py
getools/utils/file_utils.py
getools/utils/gen_utils.py
getools/utils/string_utils.py
getools-0.1.4.dist-info/WHEEL
getools-0.1.4.dist-info/METADATA
getools-0.1.4.dist-info/RECORD
