Metadata-Version: 2.1
Name: getools
Version: 0.1.4
Summary: Genetics, Evolution and Bioinformatic tools
Author: russellmyers
Author-email: flipside@netspace.net.au
Requires-Python: >=3.6,<4.0
Classifier: Programming Language :: Python :: 3
Classifier: Programming Language :: Python :: 3.6
Classifier: Programming Language :: Python :: 3.7
Classifier: Programming Language :: Python :: 3.8
Classifier: Programming Language :: Python :: 3.9
Requires-Dist: numpy (>=1.18.1,<2.0.0)
Requires-Dist: scipy (>=1.4.1,<2.0.0)
